metisfl/__init__.py
metisfl/common/__init__.py
metisfl/common/client.py
metisfl/common/config.py
metisfl/common/formatting.py
metisfl/common/logger.py
metisfl/common/server.py
metisfl/common/types.py
metisfl/common/utils.py
metisfl/controller/__init__.py
metisfl/controller/controller.so
metisfl/controller/controller_instance.py
metisfl/driver/__init__.py
metisfl/driver/clients.py
metisfl/driver/driver.py
metisfl/driver/monitor.py
metisfl/encryption/__init__.py
metisfl/encryption/fhe.so
metisfl/encryption/homomorphic.py
metisfl/encryption/scheme.py
metisfl/helpers/__init__.py
metisfl/helpers/ckks.py
metisfl/helpers/ssl.py
metisfl/learner/__init__.py
metisfl/learner/app.py
metisfl/learner/client.py
metisfl/learner/learner.py
metisfl/learner/message.py
metisfl/learner/server.py
metisfl/learner/tasks.py
metisfl/proto/__init__.py
metisfl/proto/controller_pb2.py
metisfl/proto/controller_pb2_grpc.py
metisfl/proto/learner_pb2.py
metisfl/proto/learner_pb2_grpc.py
metisfl/proto/model_pb2.py
metisfl/proto/model_pb2_grpc.py
metisfl/proto/proto_messages_factory.py
metisfl/proto/protoc.py
metisfl/proto/service_common_pb2.py
metisfl/proto/service_common_pb2_grpc.py
metisfl-1.0.0.data/data/metisfl/controller/controller.so
metisfl-1.0.0.data/data/metisfl/encryption/fhe.so
metisfl-1.0.0.dist-info/LICENSE
metisfl-1.0.0.dist-info/METADATA
metisfl-1.0.0.dist-info/WHEEL
metisfl-1.0.0.dist-info/top_level.txt
metisfl-1.0.0.dist-info/RECORD
