Metadata-Version: 2.1
Name: metisfl
Version: 1.0.0
Summary: MetisFL: The developer-friendly federated learning framework
Home-page: https://github.com/nevronai/metisfl
Author: MetisFL Team
Author-email: hello@nevron.ai
Classifier: Development Status :: 2 - Pre-Alpha
Classifier: Intended Audience :: Developers
Classifier: Topic :: Software Development :: Testing
Classifier: Topic :: Software Development :: Libraries
Classifier: Programming Language :: Python
Classifier: Programming Language :: Python :: 3.8
Classifier: Programming Language :: Python :: 3.9
Classifier: Programming Language :: Python :: 3.10
Classifier: Programming Language :: C++
Requires-Python: >=3.9, <3.10
License-File: LICENSE
Requires-Dist: Pebble >=5.0.3
Requires-Dist: PyYAML >=6.0
Requires-Dist: pandas >=1.3.2
Requires-Dist: protobuf >=4.23.4
Requires-Dist: termcolor >=2.3.0
Requires-Dist: pyfiglet >=0.8.post1
Requires-Dist: loguru >=0.7.1
